textual_demo/__about__.py
textual_demo/__init__.py
textual_demo/run.py
textual_demo-1.0.3.dist-info/METADATA
textual_demo-1.0.3.dist-info/WHEEL
textual_demo-1.0.3.dist-info/entry_points.txt
textual_demo-1.0.3.dist-info/licenses/LICENSE
textual_demo-1.0.3.dist-info/RECORD
