Metadata-Version: 2.3
Name: textual-demo
Version: 1.0.3
Summary: The Textual demo, packaged for your convenience
Project-URL: Documentation, https://github.com/Textualize/textual-demo#readme
Project-URL: Issues, https://github.com/Textualize/textual-demo/issues
Project-URL: Source, https://github.com/Textualize/textual-demo
Author-email: Will McGugan <willmcgugan@gmail.com>
License: MIT
Classifier: Development Status :: 4 - Beta
Classifier: Programming Language :: Python
Classifier: Programming Language :: Python :: 3.8
Classifier: Programming Language :: Python :: 3.9
Classifier: Programming Language :: Python :: 3.10
Classifier: Programming Language :: Python :: 3.11
Classifier: Programming Language :: Python :: 3.12
Classifier: Programming Language :: Python :: Implementation :: CPython
Classifier: Programming Language :: Python :: Implementation :: PyPy
Requires-Python: >=3.11
Requires-Dist: httpx>=0.27.2
Requires-Dist: textual[syntax]>=0.86.1
